gemstone/__init__.py
gemstone/cli.py
gemstone/dir.py
gemstone/generic_helpers.py
gemstone/iofile.py
gemstone/jobid.py
gemstone/params.py
gemstone/paths.py
gemstone/pipeliner.py
gemstone/specs.py
gemstone/stage.py
gemstone/stageflows.py
gemstone/standards.py
gemstone/testing.py
gemstone_engine-1.2.1.dist-info/licenses/LICENSE
gemstone_engine-1.2.1.dist-info/METADATA
gemstone_engine-1.2.1.dist-info/WHEEL
gemstone_engine-1.2.1.dist-info/entry_points.txt
gemstone_engine-1.2.1.dist-info/top_level.txt
gemstone_engine-1.2.1.dist-info/RECORD
