Metadata-Version: 2.4
Name: gemstone_engine
Version: 1.2.1
Summary: GEMSTONe: Generic Engine for Modular Software Task Orchestration and Negotiation
Author-email: Milo Fryling <milo.fryling@duke.edu>
License: CC BY-ND 4.0
Classifier: Programming Language :: Python :: 3
Requires-Python: >=3.8
License-File: LICENSE
Dynamic: license-file
